lob_hlpr/__init__.py
lob_hlpr/hlpr.py
lob_hlpr/lib_types.py
lob_hlpr/py.typed
lob_hlpr-0.0.6.dist-info/licenses/LICENSE
lob_hlpr-0.0.6.dist-info/METADATA
lob_hlpr-0.0.6.dist-info/WHEEL
lob_hlpr-0.0.6.dist-info/top_level.txt
lob_hlpr-0.0.6.dist-info/RECORD
