Metadata-Version: 2.4
Name: lob-hlpr
Version: 0.0.6
Summary: Simple python based helpers for lobaro tools.
Author-email: Kevin Weiss <weiss.kevin604@gmail.com>
License: The MIT License (MIT)
Classifier: Development Status :: 5 - Production/Stable
Classifier: Programming Language :: Python
Classifier: Programming Language :: Python :: 3 :: Only
Classifier: Programming Language :: Python :: 3.10
Classifier: Programming Language :: Python :: 3.11
Classifier: Programming Language :: Python :: 3.12
Requires-Python: >=3.10
License-File: LICENSE
Provides-Extra: testing
Requires-Dist: pytest~=8.3.4; extra == "testing"
Requires-Dist: pytest-cov~=6.0.0; extra == "testing"
Dynamic: license-file
